conversa/__init__.py
conversa/main.py
conversa/usefull_functions.py
conversa-1.0.0.dist-info/LICENSE
conversa-1.0.0.dist-info/METADATA
conversa-1.0.0.dist-info/WHEEL
conversa-1.0.0.dist-info/top_level.txt
conversa-1.0.0.dist-info/RECORD
