Metadata-Version: 2.1
Name: conversa
Version: 1.0.0
Summary: Convert units of measurement to others
Author: Schkimansky
Author-email: <ahmadchawla1432@gmail.com>
Keywords: python,units,conversion,convert,time,distance,length
Classifier: Development Status :: 5 - Production/Stable
Classifier: Intended Audience :: Developers
Classifier: Programming Language :: Python :: 3
Classifier: Operating System :: Unix
Classifier: Operating System :: MacOS :: MacOS X
Classifier: Operating System :: Microsoft :: Windows
License-File: LICENSE
